{
    "promotions": {
        "showPromoRail": true,
        "railTitle": "HBCU 2024-25 Basketball",
        "showTitle": true,
        "railContent": [
            {
                "displayTitle": "2024 HBCU Go Football Schedule",
                "destinationUrl": "https://weathergroup.wixstudio.com/hbcugo/basketball-schedule",
                "image": "https://static.wixstatic.com/media/f8942f_598d5186d28a4bf29c88c26e66ead569~mv2.jpg",
                "displayOrder": 1
            },
            {
                "displayTitle": "How to Watch HBCU Go",
                "destinationUrl": "https://weathergroup.wixstudio.io/hbcugo",
                "image": "https://static.wixstatic.com/media/f8942f_d4ca898f2c2d4ab8a7ff5bf3bd8a0355~mv2.jpg",
                "displayOrder": 2
            },
            {
                "displayTitle": "The Grio : HBCU Coverage",
                "destinationUrl": "https://thegrio.com/category/lifestyle/hbcu/",
                "image": "https://static.wixstatic.com/media/cb1100_126550a9a8fc4a6097b9028087fb313d~mv2.jpg",
                "displayOrder": 3
            }
        ]
    }
}